<?xml version="1.0" encoding="UTF-8"?>
<card assignedToUserID="1" id="22" taskCount="0" title="03 - Editar matricula">&#x0A;<contents/>&#x0A;<estimate>24.0</estimate>&#x0A;<status>Started</status>&#x0A;<history>&#x0A;<event name="creation" tmst="2022-12-04 22:00" user="admin"/>&#x0A;<event name="statusProposed" tmst="2022-12-04 22:00" user="admin"/>&#x0A;<event name="statusStarted" tmst="2022-12-04 22:03" user="admin"/>&#x0A;<event name="lastChange" tmst="2022-12-04 22:03" user="admin"/>&#x0A;</history>&#x0A;<taskList/>&#x0A;<fieldList/>&#x0A;<acceptanceTestList/>&#x0A;</card>